setup.py
fig_py/__init__.py
fig_py/cli.py
fig_py/create_template.py
fig_py/github.py
fig_py/util.py
fig_py.egg-info/PKG-INFO
fig_py.egg-info/SOURCES.txt
fig_py.egg-info/dependency_links.txt
fig_py.egg-info/eager_resources.txt
fig_py.egg-info/entry_points.txt
fig_py.egg-info/namespace_packages.txt
fig_py.egg-info/not-zip-safe
fig_py.egg-info/requires.txt
fig_py.egg-info/top_level.txt