Metadata-Version: 1.1
Name: fig-py
Version: 0.0.3
Summary: An utility for configuring python projects from jinja templates.
Home-page: http://github.com/newslynx/fig-py
Author: Brian Abelson
Author-email: brian@newslynx.org
License: MIT
Platform: UNKNOWN
Classifier: Development Status :: 3 - Alpha
Classifier: Intended Audience :: Developers
Classifier: License :: OSI Approved :: MIT License
Classifier: Operating System :: OS Independent
Classifier: Programming Language :: Python
